nanohubpadre/__init__.py
nanohubpadre/base.py
nanohubpadre/contact.py
nanohubpadre/doping.py
nanohubpadre/electrode.py
nanohubpadre/interface.py
nanohubpadre/log.py
nanohubpadre/material.py
nanohubpadre/mesh.py
nanohubpadre/models.py
nanohubpadre/options.py
nanohubpadre/outputs.py
nanohubpadre/parser.py
nanohubpadre/plot3d.py
nanohubpadre/plotting.py
nanohubpadre/region.py
nanohubpadre/regrid.py
nanohubpadre/simulation.py
nanohubpadre/solution.py
nanohubpadre/solver.py
nanohubpadre/use.py
nanohubpadre/visualization.py
nanohubpadre/devices/__init__.py
nanohubpadre/devices/bjt.py
nanohubpadre/devices/mesfet.py
nanohubpadre/devices/mos_capacitor.py
nanohubpadre/devices/mosfet.py
nanohubpadre/devices/pn_diode.py
nanohubpadre/devices/schottky_diode.py
nanohubpadre/devices/solar_cell.py
nanohub_padre-0.0.2.dist-info/METADATA
nanohub_padre-0.0.2.dist-info/WHEEL
nanohub_padre-0.0.2.dist-info/top_level.txt
nanohub_padre-0.0.2.dist-info/RECORD
