Metadata-Version: 2.4
Name: nanohub-padre
Version: 0.0.2
Summary: Python library for creating and running PADRE semiconductor device simulations
Home-page: https://github.com/nanohub/nanohub-padre
Author: nanohub-padre Contributors
Author-email: 
License: MIT
Project-URL: Documentation, https://nanohub-padre.readthedocs.io/
Project-URL: Repository, https://github.com/nanohub/padre
Project-URL: Issues, https://github.com/nanohub/padre/issues
Keywords: semiconductor,device simulation,PADRE,TCAD
Classifier: Development Status :: 3 - Alpha
Classifier: Intended Audience :: Science/Research
Classifier: License :: OSI Approved :: MIT License
Classifier: Operating System :: OS Independent
Classifier: Programming Language :: Python :: 3
Classifier: Programming Language :: Python :: 3.7
Classifier: Programming Language :: Python :: 3.8
Classifier: Programming Language :: Python :: 3.9
Classifier: Programming Language :: Python :: 3.10
Classifier: Programming Language :: Python :: 3.11
Classifier: Topic :: Scientific/Engineering :: Electronic Design Automation (EDA)
Classifier: Topic :: Scientific/Engineering :: Physics
Requires-Python: >=3.8
Provides-Extra: dev
Requires-Dist: pytest>=6.0; extra == "dev"
Requires-Dist: pytest-cov; extra == "dev"
Provides-Extra: docs
Requires-Dist: sphinx>=4.0; extra == "docs"
Requires-Dist: sphinx-rtd-theme>=1.0; extra == "docs"
Dynamic: home-page
Dynamic: requires-python
